user_secrets/__init__.py
user_secrets/admin.py
user_secrets/apps.py
user_secrets/auth_backend.py
user_secrets/caches.py
user_secrets/checks.py
user_secrets/constants.py
user_secrets/crypto.py
user_secrets/exceptions.py
user_secrets/forms.py
user_secrets/middleware.py
user_secrets/model_fields.py
user_secrets/models.py
user_secrets/publish.py
user_secrets/signals.py
user_secrets/user_key.py
user_secrets_tests/__init__.py
user_secrets_tests/admin.py
user_secrets_tests/apps.py
user_secrets_tests/forms.py
user_secrets_tests/management/__init__.py
user_secrets_tests/management/commands/__init__.py
user_secrets_tests/management/commands/run_testserver.py
user_secrets_tests/media/.gitkeep
user_secrets_tests/models.py
user_secrets_tests/settings.py
user_secrets_tests/static/.gitkeep
user_secrets_tests/templates/admin/base_site.html
user_secrets_tests/templates/demo/base.html
user_secrets_tests/templates/demo/display_example_secret.html
user_secrets_tests/templates/demo/edit_example_secret.html
user_secrets_tests/templates/demo/footer.html
user_secrets_tests/tests/__init__.py
user_secrets_tests/tests/test_admin.py
user_secrets_tests/tests/test_basics.py
user_secrets_tests/tests/test_crypto.py
user_secrets_tests/tests/test_example_app_display.py
user_secrets_tests/tests/test_example_app_edit.py
user_secrets_tests/urls.py
user_secrets_tests/views/__init__.py
user_secrets_tests/views/display.py
user_secrets_tests/views/edit.py
django_user_secrets-0.2.0.dist-info/entry_points.txt
django_user_secrets-0.2.0.dist-info/LICENSE
django_user_secrets-0.2.0.dist-info/WHEEL
django_user_secrets-0.2.0.dist-info/METADATA
django_user_secrets-0.2.0.dist-info/RECORD
